odoo10_addon_hr_holidays_compute_days-10.0.3.1.1-nspkg.pth
odoo/addons/hr_holidays_compute_days/README.rst
odoo/addons/hr_holidays_compute_days/__init__.py
odoo/addons/hr_holidays_compute_days/__manifest__.py
odoo/addons/hr_holidays_compute_days/hooks.py
odoo/addons/hr_holidays_compute_days/i18n/ar.po
odoo/addons/hr_holidays_compute_days/i18n/cs_CZ.po
odoo/addons/hr_holidays_compute_days/i18n/de.po
odoo/addons/hr_holidays_compute_days/i18n/es.po
odoo/addons/hr_holidays_compute_days/i18n/fi.po
odoo/addons/hr_holidays_compute_days/i18n/fr.po
odoo/addons/hr_holidays_compute_days/i18n/hr.po
odoo/addons/hr_holidays_compute_days/i18n/hr_HR.po
odoo/addons/hr_holidays_compute_days/i18n/hr_holidays_compute_days.pot
odoo/addons/hr_holidays_compute_days/i18n/it.po
odoo/addons/hr_holidays_compute_days/i18n/lt.po
odoo/addons/hr_holidays_compute_days/i18n/nl_NL.po
odoo/addons/hr_holidays_compute_days/i18n/pt_BR.po
odoo/addons/hr_holidays_compute_days/i18n/ro.po
odoo/addons/hr_holidays_compute_days/i18n/sl.po
odoo/addons/hr_holidays_compute_days/models/__init__.py
odoo/addons/hr_holidays_compute_days/models/hr_employee.py
odoo/addons/hr_holidays_compute_days/models/hr_holidays.py
odoo/addons/hr_holidays_compute_days/models/hr_holidays_status.py
odoo/addons/hr_holidays_compute_days/models/resource_calendar.py
odoo/addons/hr_holidays_compute_days/readme/CONFIGURE.rst
odoo/addons/hr_holidays_compute_days/readme/CONTRIBUTORS.rst
odoo/addons/hr_holidays_compute_days/readme/DESCRIPTION.rst
odoo/addons/hr_holidays_compute_days/readme/USAGE.rst
odoo/addons/hr_holidays_compute_days/static/description/icon.png
odoo/addons/hr_holidays_compute_days/static/description/index.html
odoo/addons/hr_holidays_compute_days/tests/__init__.py
odoo/addons/hr_holidays_compute_days/tests/test_holidays_compute_days.py
odoo/addons/hr_holidays_compute_days/views/hr_holidays_status_views.xml
odoo/addons/hr_holidays_compute_days/views/hr_holidays_views.xml
odoo10_addon_hr_holidays_compute_days-10.0.3.1.1.dist-info/METADATA
odoo10_addon_hr_holidays_compute_days-10.0.3.1.1.dist-info/WHEEL
odoo10_addon_hr_holidays_compute_days-10.0.3.1.1.dist-info/namespace_packages.txt
odoo10_addon_hr_holidays_compute_days-10.0.3.1.1.dist-info/top_level.txt
odoo10_addon_hr_holidays_compute_days-10.0.3.1.1.dist-info/RECORD
