Metadata-Version: 2.1
Name: odoo10-addon-hr-holidays-compute-days
Version: 10.0.3.1.1
Summary: Computes the actual leave days considering rest days and public holidays
Home-page: https://github.com/OCA/hr
Author: iDT LABS, Tecnativa, Odoo Community Association (OCA)
Author-email: support@odoo-community.org
License: AGPL-3
Platform: UNKNOWN
Classifier: Programming Language :: Python
Classifier: Framework :: Odoo
Classifier: License :: OSI Approved :: GNU Affero General Public License v3
Requires-Python: ~=2.7
Requires-Dist: odoo10-addon-hr-public-holidays
Requires-Dist: odoo (<10.1dev,>=10.0)
